bluechi/__init__.py
bluechi/api.py
bluechi/ext.py
bluechi-1.2.0.dist-info/licenses/LICENSE
bluechi-1.2.0.dist-info/METADATA
bluechi-1.2.0.dist-info/WHEEL
bluechi-1.2.0.dist-info/top_level.txt
bluechi-1.2.0.dist-info/zip-safe
bluechi-1.2.0.dist-info/RECORD
