Metadata-Version: 2.4
Name: bluechi
Version: 1.2.0
Summary: Python bindings for BlueChi's D-Bus API
Home-page: https://github.com/eclipse-bluechi/bluechi/
Author: BlueChi developers
Author-email: BlueChi developers <bluechi-dev@eclipse.org>
Project-URL: Homepage, https://github.com/eclipse-bluechi/bluechi/
Project-URL: Documentation, https://bluechi.readthedocs.io/en/latest/
Project-URL: Repository, https://github.com/eclipse-bluechi/bluechi/
Project-URL: Issues, https://github.com/eclipse-bluechi/bluechi/issues
Keywords: bluechi,python,D-Bus,systemd
Classifier: Programming Language :: Python
Classifier: Programming Language :: Python :: 3
Requires-Python: >=3.9
License-File: LICENSE
Requires-Dist: dasbus
Dynamic: author
Dynamic: home-page
Dynamic: license-file
Dynamic: requires-python
